netbox_attachments/__init__.py
netbox_attachments/filtersets.py
netbox_attachments/forms.py
netbox_attachments/models.py
netbox_attachments/navigation.py
netbox_attachments/search.py
netbox_attachments/tables.py
netbox_attachments/template_content.py
netbox_attachments/urls.py
netbox_attachments/utils.py
netbox_attachments/version.py
netbox_attachments/views.py
netbox_attachments/api/__init__.py
netbox_attachments/api/serializers.py
netbox_attachments/api/urls.py
netbox_attachments/api/views.py
netbox_attachments/migrations/0001_initial.py
netbox_attachments/migrations/0002_alter_netboxattachment_options_and_more.py
netbox_attachments/migrations/0003_alter_netboxattachment_name.py
netbox_attachments/migrations/0004_netboxattachment_size_and_more.py
netbox_attachments/migrations/0005_netboxattachment_description.py
netbox_attachments/migrations/0006_rename_content_type_netboxattachment_object_type.py
netbox_attachments/migrations/0007_alter_netboxattachment_object_type.py
netbox_attachments/migrations/__init__.py
netbox_attachments/templates/netbox_attachments/__init__.py
netbox_attachments/templates/netbox_attachments/add_attachment_button.html
netbox_attachments/templates/netbox_attachments/generic_tab_list.html
netbox_attachments/templates/netbox_attachments/netbox_attachment_edit.html
netbox_attachments/templates/netbox_attachments/netbox_attachment_panel.html
netbox_attachments/templates/netbox_attachments/netboxattachment.html
netbox_attachments/tests/__init__.py
netbox_attachments/tests/test_configuration.py
netbox_attachments/tests/test_template_extensions.py
netbox_attachments-10.0.1.dist-info/licenses/LICENSE
netbox_attachments-10.0.1.dist-info/METADATA
netbox_attachments-10.0.1.dist-info/WHEEL
netbox_attachments-10.0.1.dist-info/top_level.txt
netbox_attachments-10.0.1.dist-info/RECORD
