Metadata-Version: 2.4
Name: netbox-attachments
Version: 10.0.1
Summary: Netbox plugin to manage attachments for any model
Home-page: https://github.com/Kani999/netbox-attachments
Author: Jan Krupa
License: Apache 2
Keywords: netbox,netbox-plugin
Classifier: Intended Audience :: Developers
Classifier: Framework :: Django
Classifier: License :: OSI Approved :: Apache Software License
Classifier: Programming Language :: Python :: 3
Classifier: Programming Language :: Python :: 3.12
Classifier: Programming Language :: Python :: 3.13
Classifier: Programming Language :: Python :: 3.14
Classifier: Operating System :: OS Independent
Requires-Python: >=3.12,<3.15
License-File: LICENSE
Dynamic: author
Dynamic: classifier
Dynamic: description
Dynamic: description-content-type
Dynamic: home-page
Dynamic: keywords
Dynamic: license
Dynamic: license-file
Dynamic: requires-python
Dynamic: summary
